pypangolin/__init__.py
pypangolin/admin.py
pypangolin/auth.py
pypangolin/catalog.py
pypangolin/client.py
pypangolin/exceptions.py
pypangolin/federated.py
pypangolin/git.py
pypangolin/governance.py
pypangolin/models.py
pypangolin/assets/__init__.py
pypangolin/assets/base.py
pypangolin/assets/delta.py
pypangolin/assets/files.py
pypangolin/assets/hudi.py
pypangolin/assets/lance.py
pypangolin/assets/other.py
pypangolin/assets/paimon.py
pypangolin/assets/vortex.py
pypangolin/assets/connections/__init__.py
pypangolin/assets/connections/base.py
pypangolin/assets/connections/flight.py
pypangolin/assets/connections/nosql.py
pypangolin/assets/connections/sql.py
pypangolin/assets/connections/warehouse.py
pypangolin-0.5.0.dist-info/METADATA
pypangolin-0.5.0.dist-info/WHEEL
pypangolin-0.5.0.dist-info/RECORD
