Metadata-Version: 2.4
Name: pypangolin
Version: 0.5.0
Summary: Python client for Pangolin Data Catalog
Project-URL: Homepage, https://github.com/AlexMercedCoder/Pangolin
Author-email: Alex Merced <alex@alexmerced.com>
License-Expression: MIT
Classifier: License :: OSI Approved :: MIT License
Classifier: Programming Language :: Python :: 3
Requires-Python: >=3.8
Requires-Dist: cryptography>=41.0.0
Requires-Dist: pydantic>=2.0.0
Requires-Dist: pyiceberg>=0.5.0
Requires-Dist: requests>=2.28.0
Provides-Extra: all
Requires-Dist: deltalake>=0.10.0; extra == 'all'
Requires-Dist: dremioframe>=0.1.0; extra == 'all'
Requires-Dist: google-cloud-bigquery>=3.0.0; extra == 'all'
Requires-Dist: lancedb>=0.1.0; extra == 'all'
Requires-Dist: mysql-connector-python>=8.0.0; extra == 'all'
Requires-Dist: psycopg2-binary>=2.9.0; extra == 'all'
Requires-Dist: pyarrow>=12.0.0; extra == 'all'
Requires-Dist: pyiceberg[adlfs,gcsfs,s3fs]; extra == 'all'
Requires-Dist: pymongo>=4.0.0; extra == 'all'
Requires-Dist: pyodbc>=4.0.0; extra == 'all'
Requires-Dist: pypaimon>=0.1.0; extra == 'all'
Requires-Dist: snowflake-connector-python>=3.0.0; extra == 'all'
Provides-Extra: all-connections
Requires-Dist: dremioframe>=0.1.0; extra == 'all-connections'
Requires-Dist: google-cloud-bigquery>=3.0.0; extra == 'all-connections'
Requires-Dist: mysql-connector-python>=8.0.0; extra == 'all-connections'
Requires-Dist: psycopg2-binary>=2.9.0; extra == 'all-connections'
Requires-Dist: pymongo>=4.0.0; extra == 'all-connections'
Requires-Dist: pyodbc>=4.0.0; extra == 'all-connections'
Requires-Dist: snowflake-connector-python>=3.0.0; extra == 'all-connections'
Provides-Extra: azure
Requires-Dist: pyiceberg[adlfs]>=0.5.0; extra == 'azure'
Provides-Extra: bigquery
Requires-Dist: google-cloud-bigquery>=3.0.0; extra == 'bigquery'
Provides-Extra: delta
Requires-Dist: deltalake>=0.10.0; extra == 'delta'
Provides-Extra: dremio
Requires-Dist: dremioframe>=0.1.0; extra == 'dremio'
Provides-Extra: gcs
Requires-Dist: pyiceberg[gcsfs]>=0.5.0; extra == 'gcs'
Provides-Extra: lance
Requires-Dist: lancedb>=0.1.0; extra == 'lance'
Provides-Extra: mongodb
Requires-Dist: pymongo>=4.0.0; extra == 'mongodb'
Provides-Extra: mysql
Requires-Dist: mysql-connector-python>=8.0.0; extra == 'mysql'
Provides-Extra: paimon
Requires-Dist: pypaimon>=0.1.0; extra == 'paimon'
Provides-Extra: postgres
Requires-Dist: psycopg2-binary>=2.9.0; extra == 'postgres'
Provides-Extra: redshift
Requires-Dist: psycopg2-binary>=2.9.0; extra == 'redshift'
Provides-Extra: s3
Requires-Dist: pyiceberg[s3fs]>=0.5.0; extra == 's3'
Provides-Extra: snowflake
Requires-Dist: snowflake-connector-python>=3.0.0; extra == 'snowflake'
Provides-Extra: synapse
Requires-Dist: pyodbc>=4.0.0; extra == 'synapse'
